vpype_watercolor/__init__.py
vpype_watercolor/watercolor.py
vpype_watercolor-0.1.0.dist-info/METADATA
vpype_watercolor-0.1.0.dist-info/WHEEL
vpype_watercolor-0.1.0.dist-info/entry_points.txt
vpype_watercolor-0.1.0.dist-info/licenses/LICENSE
vpype_watercolor-0.1.0.dist-info/RECORD
