Metadata-Version: 2.4
Name: vpype-watercolor
Version: 0.1.0
Summary: vpype plugin for watercolor plotting
License-Expression: MIT
License-File: LICENSE
Requires-Python: >=3.10
Requires-Dist: click
Requires-Dist: svgelements
Requires-Dist: vpype>=1.14
